alu.v
module ALU(
    input [3:0] A,
    input [3:0] B,
    input [3:0] Sel,
    output [3:0] ALU_out,
    output CarryOut
);

    reg [3:0] ALU_result;
    wire [4:0] tmp;

    assign ALU_out = ALU_result;
    assign tmp = {1'b0, A} + {1'b0, B};
    assign CarryOut = tmp[4];

    always @(*) begin
        case (Sel)
            4'b0000: ALU_result = A + B;
            4'b0001: ALU_result = A - B;
            4'b0010: ALU_result = A * B;
            4'b0011: ALU_result = A / B;
            4'b0100: ALU_result = A << 1;
            4'b0101: ALU_result = A >> 1;
            4'b0110: ALU_result = {A[2:0], A[3]};
            4'b0111: ALU_result = {A[0], A[3:1]};
            4'b1000: ALU_result = A & B;
            4'b1001: ALU_result = A | B;
            4'b1010: ALU_result = A ^ B;
            4'b1011: ALU_result = ~(A | B);
            4'b1100: ALU_result = ~(A & B);
            4'b1101: ALU_result = ~(A ^ B);
            4'b1110: ALU_result = (A < B) ? 4'd1 : 4'd0;
            4'b1111: ALU_result = (A == B) ? 4'd1 : 4'd0;
            default: ALU_result = 4'd0;
        endcase
    end
endmodule

alu_tb.v
`timescale 1ns/1ps

module ALU_tb;

    reg [3:0] A, B, Sel;
    wire [3:0] ALU_out;
    wire CarryOut;

    ALU uut (
        .A(A),
        .B(B),
        .Sel(Sel),
        .ALU_out(ALU_out),
        .CarryOut(CarryOut)
    );

    initial begin
        $dumpfile("ALU_tb.vcd");
        $dumpvars(0, ALU_tb);

        $display("Time\tA\tB\tSel\tALU_out\tCarryOut");
        $monitor("%g\t%h\t%h\t%b\t%h\t%b", $time, A, B, Sel, ALU_out, CarryOut);

        A = 4'b0011; B = 4'b0001; Sel = 4'b0000; #10; // A + B = 4
        A = 4'b0100; B = 4'b0010; Sel = 4'b0001; #10; // A - B = 2
        A = 4'b0011; B = 4'b0010; Sel = 4'b0010; #10; // A * B = 6
        A = 4'b1000; B = 4'b0010; Sel = 4'b0011; #10; // A / B = 4
        A = 4'b0101; Sel = 4'b0100; #10; // A << 1 = A*2
        A = 4'b1000; Sel = 4'b0101; #10; // A >> 1 = 4
        A = 4'b1101; Sel = 4'b0110; #10; // rotate left
        A = 4'b1101; Sel = 4'b0111; #10; // rotate right
        A = 4'b1100; B = 4'b1010; Sel = 4'b1000; #10; // AND
        A = 4'b1100; B = 4'b1010; Sel = 4'b1001; #10; // OR
        A = 4'b1100; B = 4'b1010; Sel = 4'b1010; #10; // XOR
        A = 4'b1100; B = 4'b1010; Sel = 4'b1011; #10; // NOR
        A = 4'b1100; B = 4'b1010; Sel = 4'b1100; #10; // NAND
        A = 4'b1100; B = 4'b1010; Sel = 4'b1101; #10; // XNOR
        A = 4'b0010; B = 4'b0100; Sel = 4'b1110; #10; // A < B
        A = 4'b0100; B = 4'b0100; Sel = 4'b1111; #10; // A == B

        $finish;
    end

endmodule

ALU_tb.vcd
$date
	Sun Jul 20 16:31:02 2025
$end
$version
	Icarus Verilog
$end
$timescale
	1ps
$end
$scope module ALU_tb $end
$var wire 1 ! CarryOut $end
$var wire 4 " ALU_out [3:0] $end
$var reg 4 # A [3:0] $end
$var reg 4 $ B [3:0] $end
$var reg 4 % Sel [3:0] $end
$scope module uut $end
$var wire 4 & A [3:0] $end
$var wire 4 ' ALU_out [3:0] $end
$var wire 4 ( B [3:0] $end
$var wire 4 ) Sel [3:0] $end
$var wire 5 * tmp [4:0] $end
$var wire 1 ! CarryOut $end
$var reg 4 + ALU_result [3:0] $end
$upscope $end
$upscope $end
$enddefinitions $end
$comment Show the parameter values. $end
$dumpall
$end
#0
$dumpvars
b100 +
b100 *
b0 )
b1 (
b100 '
b11 &
b0 %
b1 $
b11 #
b100 "
0!
$end
#10000
b10 "
b10 '
b10 +
b1 %
b1 )
b10 $
b10 (
b110 *
b100 #
b100 &
#20000
b110 "
b110 '
b110 +
b10 %
b10 )
b101 *
b11 #
b11 &
#30000
b100 "
b100 '
b100 +
b11 %
b11 )
b1010 *
b1000 #
b1000 &
#40000
b1010 "
b1010 '
b1010 +
b100 %
b100 )
b111 *
b101 #
b101 &
#50000
b100 "
b100 '
b100 +
b101 %
b101 )
b1010 *
b1000 #
b1000 &
#60000
b1011 "
b1011 '
b1011 +
b110 %
b110 )
b1111 *
b1101 #
b1101 &
#70000
b1110 "
b1110 '
b1110 +
b111 %
b111 )
#80000
1!
b1000 "
b1000 '
b1000 +
b1000 %
b1000 )
b1010 $
b1010 (
b10110 *
b1100 #
b1100 &
#90000
b1110 "
b1110 '
b1110 +
b1001 %
b1001 )
#100000
b110 "
b110 '
b110 +
b1010 %
b1010 )
#110000
b1 "
b1 '
b1 +
b1011 %
b1011 )
#120000
b111 "
b111 '
b111 +
b1100 %
b1100 )
#130000
b1001 "
b1001 '
b1001 +
b1101 %
b1101 )
#140000
b1 "
b1 '
b1 +
0!
b1110 %
b1110 )
b100 $
b100 (
b110 *
b10 #
b10 &
#150000
b1111 %
b1111 )
b1000 *
b100 #
b100 &
